frameguard/__init__.py
frameguard/frameguard.py
tests/__init__.py
tests/test_frameguard.py
frameguard-0.1.1.dist-info/LICENSE
frameguard-0.1.1.dist-info/METADATA
frameguard-0.1.1.dist-info/WHEEL
frameguard-0.1.1.dist-info/top_level.txt
frameguard-0.1.1.dist-info/RECORD
