Metadata-Version: 2.1
Name: frameguard
Version: 0.1.1
Summary: Validated Pandas DataFrames
Home-page: https://github.com/hnnhvwht/frameguard
Author: Hannah White
Author-email: hannah.white@tutanota.com
License: MIT
Project-URL: Source, https://github.com/hnnhvwht/frameguard
Keywords: pandas dataframe validation
Platform: UNKNOWN
Classifier: Development Status :: 3 - Alpha
Classifier: Intended Audience :: Science/Research
Classifier: License :: OSI Approved :: MIT License
Classifier: Programming Language :: Python :: 3.7
Classifier: Topic :: Scientific/Engineering
Classifier: Topic :: Software Development :: Libraries :: Python Modules
Requires-Python: >=3.7
Requires-Dist: numpy (>=1.19.1)
Requires-Dist: pandas (>=1.1.0)
Requires-Dist: pyyaml (>=5.3.1)
